merge_text_boxes/__init__.py
merge_text_boxes/main.py
merge_text_boxes-0.0.2.dist-info/LICENSE
merge_text_boxes-0.0.2.dist-info/METADATA
merge_text_boxes-0.0.2.dist-info/WHEEL
merge_text_boxes-0.0.2.dist-info/top_level.txt
merge_text_boxes-0.0.2.dist-info/RECORD
