Metadata-Version: 2.1
Name: merge-text-boxes
Version: 0.0.2
Summary: Merge text boxes in the same row or column.
Home-page: https://github.com/SWHL/MergeTextBoxes
Author: SWHL
Author-email: liekkaskono@163.com
License: Apache-2.0
Keywords: text-detections,merge-text-boxes
Platform: Any
Classifier: Programming Language :: Python :: 3.6
Classifier: Programming Language :: Python :: 3.7
Classifier: Programming Language :: Python :: 3.8
Classifier: Programming Language :: Python :: 3.9
Classifier: Programming Language :: Python :: 3.10
Classifier: Programming Language :: Python :: 3.11
Requires-Python: >=3.6,<3.12
Requires-Dist: numpy
Requires-Dist: opencv-python
